prefpicker/__init__.py
prefpicker/__main__.py
prefpicker/main.py
prefpicker/prefpicker.py
prefpicker/py.typed
prefpicker/test_main.py
prefpicker/test_prefpicker.py
prefpicker/test_templates.py
prefpicker/templates/browser-fuzzing.yml
prefpicker/templates/schema.json
prefpicker-2.18.0.dist-info/licenses/LICENSE
prefpicker-2.18.0.dist-info/METADATA
prefpicker-2.18.0.dist-info/WHEEL
prefpicker-2.18.0.dist-info/entry_points.txt
prefpicker-2.18.0.dist-info/top_level.txt
prefpicker-2.18.0.dist-info/RECORD
