Metadata-Version: 2.4
Name: prefpicker
Version: 2.18.0
Summary: PrefPicker - Manage & generate prefs.js files
Home-page: https://github.com/MozillaSecurity/prefpicker
Author: Tyson Smith
Author-email: twsmith@mozilla.com
Maintainer: Mozilla Fuzzing Team
Maintainer-email: fuzzing@mozilla.com
License: MPL 2.0
Keywords: firefox fuzz fuzzing test testing
Classifier: License :: OSI Approved :: Mozilla Public License 2.0 (MPL 2.0)
Classifier: Programming Language :: Python :: 3
Classifier: Topic :: Software Development :: Testing
Requires-Python: >=3.10
License-File: LICENSE
Requires-Dist: PyYAML
Provides-Extra: dev
Requires-Dist: pre-commit; extra == "dev"
Requires-Dist: tox; extra == "dev"
Dynamic: license-file
